bro_listen/__init__.py
bro_listen/bro_listen.py
bro_listen/chat.py
bro_listen/config.toml
bro_listen/utils.py
bro_listen/voice.py
bro_listen-0.2.0.dist-info/entry_points.txt
bro_listen-0.2.0.dist-info/LICENSE.md
bro_listen-0.2.0.dist-info/WHEEL
bro_listen-0.2.0.dist-info/METADATA
bro_listen-0.2.0.dist-info/RECORD
