Metadata-Version: 2.1
Name: bro-listen
Version: 0.2.0
Summary: Interact with openAI API with voice
Home-page: https://github.com/mikkac/bro_listen
License: MIT License (MIT)
Keywords: voice recognition,chat,transcription,vosk,openai
Author: Mikolaj Kaczmarek
Author-email: m.kaczmarek9@gmail.com
Requires-Python: >=3.8,<4.0
Classifier: Development Status :: 4 - Beta
Classifier: Environment :: Console
Classifier: License :: OSI Approved :: MIT License
Classifier: License :: Other/Proprietary License
Classifier: Operating System :: MacOS
Classifier: Operating System :: Microsoft :: Windows
Classifier: Operating System :: POSIX :: Linux
Classifier: Programming Language :: Python
Classifier: Programming Language :: Python :: 3
Classifier: Programming Language :: Python :: 3.10
Classifier: Programming Language :: Python :: 3.8
Classifier: Programming Language :: Python :: 3.9
Requires-Dist: openai (>=0.25.0,<0.26.0)
Requires-Dist: pyttsx3 (>=2.90,<3.0)
Requires-Dist: rich (>=12.6.0,<13.0.0)
Requires-Dist: sounddevice (>=0.4.5,<0.5.0)
Requires-Dist: toml (>=0.10.2,<0.11.0)
Requires-Dist: vosk (>=0.3.45,<0.4.0)
